[{"name":"dbg.main","offset":10144,"ninstr":204,"nargs":2,"nlocals":1,"size":973,"stack":88,"type":"sym","blocks":[{"offset":10144,"size":152,"jump":10296,"ops":[{"offset":10144,"esil":"","refptr":false,"fcn_addr":10144,"fcn_last":11113,"size":4,"opcode":"endbr64","disasm":"endbr64","bytes":"f30f1efa","family":"cpu","type":"null","reloc":false,"type_num":0,"type2_num":0,"flags":["main","sym.main"],"comment":"aW50IG1haW4oaW50IGFyZ2MsY2hhciAqKiBhcmd2KTs=","xrefs":[{"addr":11144,"type":"DATA"}]},{"offset":10148,"esil":"r15,8,rsp,-,=[8],8,rsp,-=","refptr":false,"fcn_addr":10144,"fcn_last":11115,"size":2,"opcode":"push r15","disasm":"push r15","bytes":"4157","family":"cpu","type":"rpush","reloc":false,"type_num":268435468,"type2_num":0},{"offset":10150,"esil":"r15d,r15,^,0xffffffff,&,r15,=,$z,zf,:=,$p,pf,:=,31,$s,sf,:=,0,cf,:=,0,of,:=","refptr":false,"fcn_addr":10144,"fcn_last":11114,"size":3,"opcode":"xor r15d, r15d","disasm":"xor r15d, r15d","bytes":"4531ff","family":"cpu","type":"xor","reloc":false,"type_num":28,"type2_num":0},{"offset":10153,"esil":"r14,8,rsp,-,=[8],8,rsp,-=","refptr":false,"fcn_addr":10144,"fcn_last":11115,"size":2,"opcode":"push r14","disasm":"push r14","bytes":"4156","family":"cpu","type":"rpush","reloc":false,"type_num":268435468,"type2_num":0},{"offset":10155,"ptr":47680,"esil":"0x928e,rip,+,r14,=","refptr":true,"fcn_addr":10144,"fcn_last":11110,"size":7,"opcode":"lea r14, [rip + 0x928e]","disasm":"lea r14, obj.longopts","bytes":"4c8d358e920000","family":"cpu","type":"lea","reloc":false,"type_num":33,"type2_num":0,"refs":[{"addr":37518,"type":"DATA"},{"addr":47680,"type":"DATA"}]},{"offset":10162,"esil":"r13,8,rsp,-,=[8],8,rsp,-=","refptr":false,"fcn_addr":10144,"fcn_last":11115,"size":2,"opcode":"push r13","disasm":"push r13","bytes":"4155","family":"cpu","type":"rpush","reloc":false,"type_num":268435468,"type2_num":0},{"offset":10164,"ptr":33030,"esil":"0x594b,rip,+,r13,=","refptr":true,"fcn_addr":10144,"fcn_last":11110,"size":7,"opcode":"lea r13, [rip + 0x594b]","disasm":"lea r13, str.b:c:d:f:nsz","bytes":"4c8d2d4b590000","family":"cpu","type":"lea","reloc":false,"type_num":33,"type2_num":0,"refs":[{"addr":22859,"type":"DATA"},{"addr":33030,"type":"DATA"}]},{"offset":10171,"esil":"r12,8,rsp,-,=[8],8,rsp,-=","refptr":false,"fcn_addr":10144,"fcn_last":11115,"size":2,"opcode":"push r12","disasm":"push r12","bytes":"4154","family":"cpu","type":"rpush","reloc":false,"type_num":268435468,"type2_num":0},{"offset":10173,"ptr":32921,"esil":"0x58d5,rip,+,r12,=","refptr":true,"fcn_addr":10144,"fcn_last":11110,"size":7,"opcode":"lea r12, [rip + 0x58d5]","disasm":"lea r12, [0x00008099]","bytes":"4c8d25d5580000","family":"cpu","type":"lea","reloc":false,"type_num":33,"type2_num":0,"refs":[{"addr":22741,"type":"DATA"},{"addr":32921,"type":"DATA"}]},{"offset":10180,"esil":"rbp,8,rsp,-,=[8],8,rsp,-=","refptr":false,"fcn_addr":10144,"fcn_last":11116,"size":1,"opcode":"push rbp","disasm":"push rbp","bytes":"55","family":"cpu","type":"rpush","reloc":false,"type_num":268435468,"type2_num":0},{"offset":10181,"esil":"edi,rbp,=","refptr":false,"fcn_addr":10144,"fcn_last":11115,"size":2,"opcode":"mov ebp, edi","disasm":"mov ebp, edi","bytes":"89fd","family":"cpu","type":"mov","reloc":false,"type_num":9,"type2_num":0},{"offset":10183,"esil":"rbx,8,rsp,-,=[8],8,rsp,-=","refptr":false,"fcn_addr":10144,"fcn_last":11116,"size":1,"opcode":"push rbx","disasm":"push rbx","bytes":"53","family":"cpu","type":"rpush","reloc":false,"type_num":268435468,"type2_num":0},{"offset":10184,"esil":"rsi,rbx,=","refptr":false,"fcn_addr":10144,"fcn_last":11114,"size":3,"opcode":"mov rbx, rsi","disasm":"mov rbx, rsi","bytes":"4889f3","family":"cpu","type":"mov","reloc":false,"type_num":9,"type2_num":0},{"offset":10187,"val":24,"esil":"24,rsp,-=,24,0x8000000000000000,-,!,63,$o,^,of,:=,63,$s,sf,:=,$z,zf,:=,$p,pf,:=,64,$b,cf,:=,3,$b,af,:=","refptr":false,"fcn_addr":10144,"fcn_last":11113,"size":4,"opcode":"sub rsp, 0x18","disasm":"sub rsp, 0x18","bytes":"4883ec18","family":"cpu","type":"sub","reloc":false,"type_num":18,"type2_num":0},{"offset":10191,"esil":"rsi,[8],rdi,=","refptr":true,"fcn_addr":10144,"fcn_last":11114,"size":3,"opcode":"mov rdi, qword [rsi]","disasm":"mov rdi, qword [rsi]","bytes":"488b3e","family":"cpu","type":"mov","reloc":false,"type_num":9,"type2_num":0},{"offset":10194,"esil":"18000,rip,8,rsp,-=,rsp,=[8],rip,=","refptr":false,"fcn_addr":10144,"fcn_last":11112,"size":5,"opcode":"call 0x4650","disasm":"call dbg.set_program_name","bytes":"e8791e0000","family":"cpu","type":"call","reloc":false,"type_num":3,"type2_num":0,"jump":18000,"fail":10199,"refs":[{"addr":18000,"type":"CALL"}]},{"offset":10199,"ptr":36993,"esil":"0x68a3,rip,+,rsi,=","refptr":true,"fcn_addr":10144,"fcn_last":11110,"size":7,"opcode":"lea rsi, [rip + 0x68a3]","disasm":"lea rsi, [0x00009081]","bytes":"488d35a3680000","family":"cpu","type":"lea","reloc":false,"type_num":33,"type2_num":0,"refs":[{"addr":26787,"type":"DATA"},{"addr":36993,"type":"DATA"}]},{"offset":10206,"val":6,"esil":"6,rdi,=","refptr":false,"fcn_addr":10144,"fcn_last":11112,"size":5,"opcode":"mov edi, 6","disasm":"mov edi, 6","bytes":"bf06000000","family":"cpu","type":"mov","reloc":false,"type_num":9,"type2_num":0},{"offset":10211,"esil":"9856,rip,8,rsp,-=,rsp,=[8],rip,=","refptr":false,"fcn_addr":10144,"fcn_last":11112,"size":5,"opcode":"call 0x2680","disasm":"call sym.imp.setlocale","bytes":"e898feffff","family":"cpu","type":"call","reloc":false,"type_num":3,"type2_num":0,"jump":9856,"fail":10216,"refs":[{"addr":9856,"type":"CALL"}]},{"offset":10216,"ptr":32962,"esil":"0x58d3,rip,+,rsi,=","refptr":true,"fcn_addr":10144,"fcn_last":11110,"size":7,"opcode":"lea rsi, [rip + 0x58d3]","disasm":"lea rsi, str._usr_local_share_locale","bytes":"488d35d3580000","family":"cpu","type":"lea","reloc":false,"type_num":33,"type2_num":0,"refs":[{"addr":22739,"type":"DATA"},{"addr":32962,"type":"DATA"}]},{"offset":10223,"esil":"r12,rdi,=","refptr":false,"fcn_addr":10144,"fcn_last":11114,"size":3,"opcode":"mov rdi, r12","disasm":"mov rdi, r12","bytes":"4c89e7","family":"cpu","type":"mov","reloc":false,"type_num":9,"type2_num":0},{"offset":10226,"esil":"9376,rip,8,rsp,-=,rsp,=[8],rip,=","refptr":false,"fcn_addr":10144,"fcn_last":11112,"size":5,"opcode":"call 0x24a0","disasm":"call sym.imp.bindtextdomain","bytes":"e8a9fcffff","family":"cpu","type":"call","reloc":false,"type_num":3,"type2_num":0,"jump":9376,"fail":10231,"refs":[{"addr":9376,"type":"CALL"}]},{"offset":10231,"esil":"r12,rdi,=","refptr":false,"fcn_addr":10144,"fcn_last":11114,"size":3,"opcode":"mov rdi, r12","disasm":"mov rdi, r12","bytes":"4c89e7","family":"cpu","type":"mov","reloc":false,"type_num":9,"type2_num":0},{"offset":10234,"ptr":35280,"esil":"0x61cf,rip,+,r12,=","refptr":true,"fcn_addr":10144,"fcn_last":11110,"size":7,"opcode":"lea r12, [rip + 0x61cf]","disasm":"lea r12, [0x000089d0]","bytes":"4c8d25cf610000","family":"cpu","type":"lea","reloc":false,"type_num":33,"type2_num":0,"refs":[{"addr":25039,"type":"DATA"},{"addr":35280,"type":"DATA"}]},{"offset":10241,"esil":"9344,rip,8,rsp,-=,rsp,=[8],rip,=","refptr":false,"fcn_addr":10144,"fcn_last":11112,"size":5,"opcode":"call 0x2480","disasm":"call sym.imp.textdomain","bytes":"e87afcffff","family":"cpu","type":"call","reloc":false,"type_num":3,"type2_num":0,"jump":9344,"fail":10246,"refs":[{"addr":9344,"type":"CALL"}]},{"offset":10246,"ptr":16512,"esil":"0x1873,rip,+,rdi,=","refptr":true,"fcn_addr":10144,"fcn_last":11110,"size":7,"opcode":"lea rdi, [rip + 0x1873]","disasm":"lea rdi, [dbg.close_stdout]","bytes":"488d3d73180000","family":"cpu","type":"lea","reloc":false,"type_num":33,"type2_num":0,"refs":[{"addr":16512,"type":"DATA"}]},{"offset":10253,"esil":"31760,rip,8,rsp,-=,rsp,=[8],rip,=","refptr":false,"fcn_addr":10144,"fcn_last":11112,"size":5,"opcode":"call 0x7c10","disasm":"call sym.atexit","bytes":"e8fe530000","family":"cpu","type":"call","reloc":false,"type_num":3,"type2_num":0,"jump":31760,"fail":10258,"refs":[{"addr":31760,"type":"CALL"}]},{"offset":10258,"ptr":49419,"val":0,"esil":"0,0x98f2,rip,+,=[1]","refptr":true,"fcn_addr":10144,"fcn_last":11110,"size":7,"opcode":"mov byte [rip + 0x98f2], 0","disasm":"mov byte [obj.suppress_non_delimited], 0","bytes":"c605f298000000","family":"cpu","type":"mov","reloc":false,"type_num":9,"type2_num":0,"refs":[{"addr":39154,"type":"DATA"},{"addr":49419,"type":"DATA"}]},{"offset":10265,"ptr":49420,"val":0,"esil":"0,0x98e9,rip,+,=[4]","refptr":true,"fcn_addr":10144,"fcn_last":11107,"size":10,"opcode":"mov dword [rip + 0x98e9], 0","disasm":"mov dword [obj.operating_mode], 0","bytes":"c705e998000000000000","family":"cpu","type":"mov","reloc":false,"type_num":9,"type2_num":0,"refs":[{"addr":39145,"type":"DATA"},{"addr":49420,"type":"DATA"}]},{"offset":10275,"ptr":49417,"val":0,"esil":"0,0x98df,rip,+,=[1]","refptr":true,"fcn_addr":10144,"fcn_last":11110,"size":7,"opcode":"mov byte [rip + 0x98df], 0","disasm":"mov byte [obj.delim], 0","bytes":"c605df98000000","family":"cpu","type":"mov","reloc":false,"type_num":9,"type2_num":0,"refs":[{"addr":39135,"type":"DATA"},{"addr":49417,"type":"DATA"}]},{"offset":10282,"ptr":49394,"val":0,"esil":"0,0x98c1,rip,+,=[1]","refptr":true,"fcn_addr":10144,"fcn_last":11110,"size":7,"opcode":"mov byte [rip + 0x98c1], 0","disasm":"mov byte [obj.have_read_stdin], 0","bytes":"c605c198000000","family":"cpu","type":"mov","reloc":false,"type_num":9,"type2_num":0,"refs":[{"addr":39105,"type":"DATA"},{"addr":49394,"type":"DATA"}]},{"offset":10289,"esil":",","refptr":false,"fcn_addr":10144,"fcn_last":11110,"size":7,"opcode":"nop dword [rax]","disasm":"nop dword [rax]","bytes":"0f1f8000000000","family":"cpu","type":"nop","reloc":false,"type_num":8,"type2_num":0}]},{"offset":10296,"size":28,"jump":10715,"fail":10324,"ops":[{"offset":10296,"esil":"r8d,r8,^,0xffffffff,&,r8,=,$z,zf,:=,$p,pf,:=,31,$s,sf,:=,0,cf,:=,0,of,:=","refptr":false,"fcn_addr":10144,"fcn_last":11114,"size":3,"opcode":"xor r8d, r8d","disasm":"xor r8d, r8d","bytes":"4531c0","family":"cpu","type":"xor","reloc":false,"type_num":28,"type2_num":0,"flags":["case.0x287b.110"],"xrefs":[{"addr":10363,"type":"CODE"},{"addr":10403,"type":"CODE"},{"addr":10415,"type":"CODE"},{"addr":10482,"type":"CODE"},{"addr":10503,"type":"CODE"},{"addr":10519,"type":"CODE"},{"addr":10563,"type":"CODE"},{"addr":10612,"type":"CODE"}]},{"offset":10299,"esil":"r14,rcx,=","refptr":false,"fcn_addr":10144,"fcn_last":11114,"size":3,"opcode":"mov rcx, r14","disasm":"mov rcx, r14","bytes":"4c89f1","family":"cpu","type":"mov","reloc":false,"type_num":9,"type2_num":0},{"offset":10302,"esil":"r13,rdx,=","refptr":false,"fcn_addr":10144,"fcn_last":11114,"size":3,"opcode":"mov rdx, r13","disasm":"mov rdx, r13","bytes":"4c89ea","family":"cpu","type":"mov","reloc":false,"type_num":9,"type2_num":0},{"offset":10305,"esil":"rbx,rsi,=","refptr":false,"fcn_addr":10144,"fcn_last":11114,"size":3,"opcode":"mov rsi, rbx","disasm":"mov rsi, rbx","bytes":"4889de","family":"cpu","type":"mov","reloc":false,"type_num":9,"type2_num":0},{"offset":10308,"esil":"ebp,rdi,=","refptr":false,"fcn_addr":10144,"fcn_last":11115,"size":2,"opcode":"mov edi, ebp","disasm":"mov edi, ebp","bytes":"89ef","family":"cpu","type":"mov","reloc":false,"type_num":9,"type2_num":0},{"offset":10310,"esil":"9456,rip,8,rsp,-=,rsp,=[8],rip,=","refptr":false,"fcn_addr":10144,"fcn_last":11112,"size":5,"opcode":"call 0x24f0","disasm":"call sym.imp.getopt_long","bytes":"e8a5fcffff","family":"cpu","type":"call","reloc":false,"type_num":3,"type2_num":0,"jump":9456,"fail":10315,"refs":[{"addr":9456,"type":"CALL"}]},{"offset":10315,"esil":"18446744073709551615,eax,==,$z,zf,:=,32,$b,cf,:=,$p,pf,:=,31,$s,sf,:=,18446744073709551615,0x80000000,-,!,31,$o,^,of,:=,3,$b,af,:=","refptr":false,"fcn_addr":10144,"fcn_last":11114,"size":3,"opcode":"cmp eax, 0xffffffff","disasm":"cmp eax, 0xffffffff","bytes":"83f8ff","family":"cpu","type":"cmp","reloc":false,"type_num":15,"type2_num":0},{"offset":10318,"esil":"zf,?{,10715,rip,=,}","refptr":false,"fcn_addr":10144,"fcn_last":11111,"size":6,"opcode":"je 0x29db","disasm":"je 0x29db","bytes":"0f8487010000","family":"cpu","type":"cjmp","reloc":false,"type_num":2147483649,"type2_num":0,"jump":10715,"fail":10324,"refs":[{"addr":10715,"type":"CODE"}]}]},{"offset":10324,"size":11,"jump":11023,"fail":10335,"ops":[{"offset":10324,"ptr":129,"val":129,"esil":"129,eax,==,$z,zf,:=,32,$b,cf,:=,$p,pf,:=,31,$s,sf,:=,129,0x80000000,-,!,31,$o,^,of,:=,3,$b,af,:=","refptr":false,"fcn_addr":10144,"fcn_last":11112,"size":5,"opcode":"cmp eax, 0x81","disasm":"cmp eax, 0x81","bytes":"3d81000000","family":"cpu","type":"cmp","reloc":false,"type_num":15,"type2_num":0,"refs":[{"addr":129,"type":"DATA"}]},{"offset":10329,"esil":"sf,of,!,^,zf,!,&,?{,11023,rip,=,}","refptr":false,"fcn_addr":10144,"fcn_last":11111,"size":6,"opcode":"jg 0x2b0f","disasm":"jg case.0x287b.101","bytes":"0f8fb0020000","family":"cpu","type":"cjmp","reloc":false,"type_num":2147483649,"type2_num":0,"jump":11023,"fail":10335,"refs":[{"addr":11023,"type":"CODE"}]}]},{"offset":10335,"size":9,"jump":10624,"fail":10344,"ops":[{"offset":10335,"ptr":97,"val":97,"esil":"97,eax,==,$z,zf,:=,32,$b,cf,:=,$p,pf,:=,31,$s,sf,:=,97,0x80000000,-,!,31,$o,^,of,:=,3,$b,af,:=","refptr":false,"fcn_addr":10144,"fcn_last":11114,"size":3,"opcode":"cmp eax, 0x61","disasm":"cmp eax, 0x61","bytes":"83f861","family":"cpu","type":"cmp","reloc":false,"type_num":15,"type2_num":0,"refs":[{"addr":97,"type":"DATA"}]},{"offset":10338,"esil":"of,sf,^,zf,|,?{,10624,rip,=,}","refptr":false,"fcn_addr":10144,"fcn_last":11111,"size":6,"opcode":"jle 0x2980","disasm":"jle 0x2980","bytes":"0f8e18010000","family":"cpu","type":"cjmp","reloc":false,"type_num":2147483649,"type2_num":0,"jump":10624,"fail":10344,"refs":[{"addr":10624,"type":"CODE"}]}]},{"offset":10344,"size":12,"jump":11023,"fail":10356,"ops":[{"offset":10344,"ptr":98,"val":98,"esil":"98,eax,-=,98,0x80000000,-,!,31,$o,^,of,:=,31,$s,sf,:=,$z,zf,:=,$p,pf,:=,32,$b,cf,:=,3,$b,af,:=","refptr":false,"fcn_addr":10144,"fcn_last":11114,"size":3,"opcode":"sub eax, 0x62","disasm":"sub eax, 0x62","bytes":"83e862","family":"cpu","type":"sub","reloc":false,"type_num":18,"type2_num":0,"refs":[{"addr":98,"type":"DATA"}]},{"offset":10347,"ptr":31,"val":31,"esil":"31,eax,==,$z,zf,:=,32,$b,cf,:=,$p,pf,:=,31,$s,sf,:=,31,0x80000000,-,!,31,$o,^,of,:=,3,$b,af,:=","refptr":false,"fcn_addr":10144,"fcn_last":11114,"size":3,"opcode":"cmp eax, 0x1f","disasm":"cmp eax, 0x1f","bytes":"83f81f","family":"cpu","type":"cmp","reloc":false,"type_num":15,"type2_num":0,"refs":[{"addr":31,"type":"DATA"}]},{"offset":10350,"esil":"cf,zf,|,!,?{,11023,rip,=,}","refptr":false,"fcn_addr":10144,"fcn_last":11111,"size":6,"opcode":"ja 0x2b0f","disasm":"ja case.0x287b.101","bytes":"0f879b020000","family":"cpu","type":"cjmp","reloc":false,"type_num":2147483649,"type2_num":0,"jump":11023,"fail":10356,"refs":[{"addr":11023,"type":"CODE"}]}]},{"offset":10356,"size":10,"switchop":{"offset":10363,"defval":0,"maxval":0,"minval":0,"cases":[{"offset":10368,"value":98,"jump":10368},{"offset":10368,"value":99,"jump":10368},{"offset":10576,"value":100,"jump":10576},{"offset":11023,"value":101,"jump":11023},{"offset":10528,"value":102,"jump":10528},{"offset":11023,"value":103,"jump":11023},{"offset":11023,"value":104,"jump":11023},{"offset":11023,"value":105,"jump":11023},{"offset":11023,"value":106,"jump":11023},{"offset":11023,"value":107,"jump":11023},{"offset":11023,"value":108,"jump":11023},{"offset":11023,"value":109,"jump":11023},{"offset":10296,"value":110,"jump":10296},{"offset":11023,"value":111,"jump":11023},{"offset":11023,"value":112,"jump":11023},{"offset":11023,"value":113,"jump":11023},{"offset":11023,"value":114,"jump":11023},{"offset":10512,"value":115,"jump":10512},{"offset":11023,"value":116,"jump":11023},{"offset":11023,"value":117,"jump":11023},{"offset":11023,"value":118,"jump":11023},{"offset":11023,"value":119,"jump":11023},{"offset":11023,"value":120,"jump":11023},{"offset":11023,"value":121,"jump":11023},{"offset":10496,"value":122,"jump":10496},{"offset":11023,"value":123,"jump":11023},{"offset":11023,"value":124,"jump":11023},{"offset":11023,"value":125,"jump":11023},{"offset":11023,"value":126,"jump":11023},{"offset":11023,"value":127,"jump":11023},{"offset":10424,"value":128,"jump":10424},{"offset":10408,"value":129,"jump":10408}]},"ops":[{"offset":10356,"esil":"32,rax,4,*,r12,+,[4],~,rax,=","refptr":true,"fcn_addr":10144,"fcn_last":11113,"size":4,"opcode":"movsxd rax, dword [r12 + rax*4]","disasm":"movsxd rax, dword [r12 + rax*4]","bytes":"49630484","family":"cpu","type":"mov","reloc":false,"type_num":9,"type2_num":0},{"offset":10360,"esil":"r12,rax,+=,63,$o,of,:=,63,$s,sf,:=,$z,zf,:=,63,$c,cf,:=,$p,pf,:=,3,$c,af,:=","refptr":false,"fcn_addr":10144,"fcn_last":11114,"size":3,"opcode":"add rax, r12","disasm":"add rax, r12","bytes":"4c01e0","family":"cpu","type":"add","reloc":false,"type_num":17,"type2_num":0},{"offset":10363,"esil":"rax,rip,=","refptr":false,"fcn_addr":10144,"fcn_last":11114,"size":3,"opcode":"jmp rax","disasm":"jmp rax","bytes":"3effe0","family":"cpu","type":"rjmp","reloc":false,"type_num":268435458,"type2_num":0,"flags":["switch.0x0000287b"],"comment":"c3dpdGNoIHRhYmxlICgzMiBjYXNlcykgYXQgMHg4OWQw","refs":[{"addr":10296,"type":"CODE"},{"addr":10368,"type":"CODE"},{"addr":10408,"type":"CODE"},{"addr":10424,"type":"CODE"},{"addr":10496,"type":"CODE"},{"addr":10512,"type":"CODE"},{"addr":10528,"type":"CODE"},{"addr":10576,"type":"CODE"},{"addr":11023,"type":"CODE"}]}]},{"offset":10368,"size":14,"jump":10990,"fail":10382,"ops":[{"offset":10368,"ptr":49420,"esil":"0x9886,rip,+,[4],rdx,=","refptr":true,"fcn_addr":10144,"fcn_last":11111,"size":6,"opcode":"mov edx, dword [rip + 0x9886]","disasm":"mov edx, dword [obj.operating_mode]","bytes":"8b1586980000","family":"cpu","type":"mov","reloc":false,"type_num":9,"type2_num":0,"flags":["case.0x287b.98","case.0x287b.99"],"refs":[{"addr":39046,"type":"DATA"},{"addr":49420,"type":"DATA"}],"xrefs":[{"addr":10363,"type":"CODE"}]},{"offset":10374,"esil":"0,edx,edx,&,==,$z,zf,:=,$p,pf,:=,31,$s,sf,:=,0,cf,:=,0,of,:=","refptr":false,"fcn_addr":10144,"fcn_last":11115,"size":2,"opcode":"test edx, edx","disasm":"test edx, edx","bytes":"85d2","family":"cpu","type":"acmp","reloc":false,"type_num":16,"type2_num":0},{"offset":10376,"esil":"zf,!,?{,10990,rip,=,}","refptr":false,"fcn_addr":10144,"fcn_last":11111,"size":6,"opcode":"jne 0x2aee","disasm":"jne 0x2aee","bytes":"0f8560020000","family":"cpu","type":"cjmp","reloc":false,"type_num":2147483649,"type2_num":0,"jump":10990,"fail":10382,"refs":[{"addr":10990,"type":"CODE"}]}]},{"offset":10382,"size":23,"jump":10296,"ops":[{"offset":10382,"ptr":49344,"esil":"0x982b,rip,+,[8],rax,=","refptr":true,"fcn_addr":10144,"fcn_last":11110,"size":7,"opcode":"mov rax, qword [rip + 0x982b]","disasm":"mov rax, qword [obj.optarg]","bytes":"488b052b980000","family":"cpu","type":"mov","reloc":false,"type_num":9,"type2_num":0,"refs":[{"addr":38955,"type":"DATA"},{"addr":49344,"type":"DATA"}]},{"offset":10389,"ptr":49420,"val":1,"esil":"1,0x986d,rip,+,=[4]","refptr":true,"fcn_addr":10144,"fcn_last":11107,"size":10,"opcode":"mov dword [rip + 0x986d], 1","disasm":"mov dword [obj.operating_mode], 1","bytes":"c7056d98000001000000","family":"cpu","type":"mov","reloc":false,"type_num":9,"type2_num":0,"refs":[{"addr":39021,"type":"DATA"},{"addr":49420,"type":"DATA"}]},{"offset":10399,"esil":"rax,rsp,=[8]","refptr":true,"fcn_addr":10144,"fcn_last":11113,"size":4,"opcode":"mov qword [rsp], rax","disasm":"mov qword [rsp], rax","bytes":"48890424","family":"cpu","type":"mov","reloc":false,"type_num":9,"type2_num":0},{"offset":10403,"esil":"0x2838,rip,=","refptr":false,"fcn_addr":10144,"fcn_last":11115,"size":2,"opcode":"jmp 0x2838","disasm":"jmp case.0x287b.110","bytes":"eb93","family":"cpu","type":"jmp","reloc":false,"type_num":1,"type2_num":0,"jump":10296,"refs":[{"addr":10296,"type":"CODE"}]}]},{"offset":10408,"size":9,"jump":10296,"ops":[{"offset":10408,"ptr":49418,"val":1,"esil":"1,0x985b,rip,+,=[1]","refptr":true,"fcn_addr":10144,"fcn_last":11110,"size":7,"opcode":"mov byte [rip + 0x985b], 1","disasm":"mov byte [obj.complement], 1","bytes":"c6055b98000001","family":"cpu","type":"mov","reloc":false,"type_num":9,"type2_num":0,"flags":["case.0x287b.129"],"refs":[{"addr":39003,"type":"DATA"},{"addr":49418,"type":"DATA"}],"xrefs":[{"addr":10363,"type":"CODE"}]},{"offset":10415,"esil":"0x2838,rip,=","refptr":false,"fcn_addr":10144,"fcn_last":11115,"size":2,"opcode":"jmp 0x2838","disasm":"jmp case.0x287b.110","bytes":"eb87","family":"cpu","type":"jmp","reloc":false,"type_num":1,"type2_num":0,"jump":10296,"refs":[{"addr":10296,"type":"CODE"}]}]},{"offset":10424,"size":24,"jump":10463,"fail":10448,"ops":[{"offset":10424,"ptr":49344,"esil":"0x9801,rip,+,[8],rdi,=","refptr":true,"fcn_addr":10144,"fcn_last":11110,"size":7,"opcode":"mov rdi, qword [rip + 0x9801]","disasm":"mov rdi, qword [obj.optarg]","bytes":"488b3d01980000","family":"cpu","type":"mov","reloc":false,"type_num":9,"type2_num":0,"flags":["case.0x287b.128"],"refs":[{"addr":38913,"type":"DATA"},{"addr":49344,"type":"DATA"}],"xrefs":[{"addr":10363,"type":"CODE"}]},{"offset":10431,"ptr":49416,"val":1,"esil":"1,0x9842,rip,+,=[1]","refptr":true,"fcn_addr":10144,"fcn_last":11110,"size":7,"opcode":"mov byte [rip + 0x9842], 1","disasm":"mov byte [obj.output_delimiter_specified], 1","bytes":"c6054298000001","family":"cpu","type":"mov","reloc":false,"type_num":9,"type2_num":0,"refs":[{"addr":38978,"type":"DATA"},{"addr":49416,"type":"DATA"}]},{"offset":10438,"val":1,"esil":"1,rax,=","refptr":false,"fcn_addr":10144,"fcn_last":11112,"size":5,"opcode":"mov eax, 1","disasm":"mov eax, 1","bytes":"b801000000","family":"cpu","type":"mov","reloc":false,"type_num":9,"type2_num":0},{"offset":10443,"val":0,"esil":"0,rdi,[1],==,$z,zf,:=,8,$b,cf,:=,$p,pf,:=,7,$s,sf,:=,0,0x80,-,!,7,$o,^,of,:=,3,$b,af,:=","refptr":true,"fcn_addr":10144,"fcn_last":11114,"size":3,"opcode":"cmp byte [rdi], 0","disasm":"cmp byte [rdi], 0","bytes":"803f00","family":"cpu","type":"cmp","reloc":false,"type_num":15,"type2_num":0},{"offset":10446,"esil":"zf,?{,10463,rip,=,}","refptr":false,"fcn_addr":10144,"fcn_last":11115,"size":2,"opcode":"je 0x28df","disasm":"je 0x28df","bytes":"740f","family":"cpu","type":"cjmp","reloc":false,"type_num":2147483649,"type2_num":0,"jump":10463,"fail":10448,"refs":[{"addr":10463,"type":"CODE"}]}]},{"offset":10448,"size":15,"jump":10463,"ops":[{"offset":10448,"esil":"rdi,0x8,rsp,+,=[8]","refptr":true,"fcn_addr":10144,"fcn_last":11112,"size":5,"opcode":"mov qword [rsp + 8], rdi","disasm":"mov qword [rsp + 8], rdi","bytes":"48897c2408","family":"cpu","type":"mov","reloc":false,"type_num":9,"type2_num":0},{"offset":10453,"esil":"9424,rip,8,rsp,-=,rsp,=[8],rip,=","refptr":false,"fcn_addr":10144,"fcn_last":11112,"size":5,"opcode":"call 0x24d0","disasm":"call sym.imp.strlen","bytes":"e8f6fbffff","family":"cpu","type":"call","reloc":false,"type_num":3,"type2_num":0,"jump":9424,"fail":10458,"refs":[{"addr":9424,"type":"CALL"}]},{"offset":10458,"esil":"0x8,rsp,+,[8],rdi,=","refptr":true,"fcn_addr":10144,"fcn_last":11112,"size":5,"opcode":"mov rdi, qword [rsp + 8]","disasm":"mov rdi, qword [rsp + 8]","bytes":"488b7c2408","family":"cpu","type":"mov","reloc":false,"type_num":9,"type2_num":0}]},{"offset":10463,"size":24,"jump":10296,"ops":[{"offset":10463,"ptr":49408,"esil":"rax,0x981a,rip,+,=[8]","refptr":true,"fcn_addr":10144,"fcn_last":11110,"size":7,"opcode":"mov qword [rip + 0x981a], rax","disasm":"mov qword [obj.output_delimiter_length], rax","bytes":"4889051a980000","family":"cpu","type":"mov","reloc":false,"type_num":9,"type2_num":0,"refs":[{"addr":38938,"type":"DATA"},{"addr":49408,"type":"DATA"}],"xrefs":[{"addr":10446,"type":"CODE"}]},{"offset":10470,"esil":"30144,rip,8,rsp,-=,rsp,=[8],rip,=","refptr":false,"fcn_addr":10144,"fcn_last":11112,"size":5,"opcode":"call 0x75c0","disasm":"call dbg.xstrdup","bytes":"e8d54c0000","family":"cpu","type":"call","reloc":false,"type_num":3,"type2_num":0,"jump":30144,"fail":10475,"refs":[{"addr":30144,"type":"CALL"}]},{"offset":10475,"ptr":49400,"esil":"rax,0x9806,rip,+,=[8]","refptr":true,"fcn_addr":10144,"fcn_last":11110,"size":7,"opcode":"mov qword [rip + 0x9806], rax","disasm":"mov qword [obj.output_delimiter_string], rax","bytes":"48890506980000","family":"cpu","type":"mov","reloc":false,"type_num":9,"type2_num":0,"refs":[{"addr":38918,"type":"DATA"},{"addr":49400,"type":"DATA"}]},{"offset":10482,"esil":"0x2838,rip,=","refptr":false,"fcn_addr":10144,"fcn_last":11112,"size":5,"opcode":"jmp 0x2838","disasm":"jmp case.0x287b.110","bytes":"e941ffffff","family":"cpu","type":"jmp","reloc":false,"type_num":1,"type2_num":0,"jump":10296,"refs":[{"addr":10296,"type":"CODE"}]}]},{"offset":10496,"size":12,"jump":10296,"ops":[{"offset":10496,"ptr":49168,"val":0,"esil":"0,0x9709,rip,+,=[1]","refptr":true,"fcn_addr":10144,"fcn_last":11110,"size":7,"opcode":"mov byte [rip + 0x9709], 0","disasm":"mov byte [obj.line_delim], 0","bytes":"c6050997000000","family":"cpu","type":"mov","reloc":false,"type_num":9,"type2_num":0,"flags":["case.0x287b.122"],"refs":[{"addr":38665,"type":"DATA"},{"addr":49168,"type":"DATA"}],"xrefs":[{"addr":10363,"type":"CODE"}]},{"offset":10503,"esil":"0x2838,rip,=","refptr":false,"fcn_addr":10144,"fcn_last":11112,"size":5,"opcode":"jmp 0x2838","disasm":"jmp case.0x287b.110","bytes":"e92cffffff","family":"cpu","type":"jmp","reloc":false,"type_num":1,"type2_num":0,"jump":10296,"refs":[{"addr":10296,"type":"CODE"}]}]},{"offset":10512,"size":12,"jump":10296,"ops":[{"offset":10512,"ptr":49419,"val":1,"esil":"1,0x97f4,rip,+,=[1]","refptr":true,"fcn_addr":10144,"fcn_last":11110,"size":7,"opcode":"mov byte [rip + 0x97f4], 1","disasm":"mov byte [obj.suppress_non_delimited], 1","bytes":"c605f497000001","family":"cpu","type":"mov","reloc":false,"type_num":9,"type2_num":0,"flags":["case.0x287b.115"],"refs":[{"addr":38900,"type":"DATA"},{"addr":49419,"type":"DATA"}],"xrefs":[{"addr":10363,"type":"CODE"}]},{"offset":10519,"esil":"0x2838,rip,=","refptr":false,"fcn_addr":10144,"fcn_last":11112,"size":5,"opcode":"jmp 0x2838","disasm":"jmp case.0x287b.110","bytes":"e91cffffff","family":"cpu","type":"jmp","reloc":false,"type_num":1,"type2_num":0,"jump":10296,"refs":[{"addr":10296,"type":"CODE"}]}]},{"offset":10528,"size":14,"jump":10990,"fail":10542,"ops":[{"offset":10528,"ptr":49420,"esil":"0x97e6,rip,+,[4],rax,=","refptr":true,"fcn_addr":10144,"fcn_last":11111,"size":6,"opcode":"mov eax, dword [rip + 0x97e6]","disasm":"mov eax, dword [obj.operating_mode]","bytes":"8b05e6970000","family":"cpu","type":"mov","reloc":false,"type_num":9,"type2_num":0,"flags":["case.0x287b.102"],"refs":[{"addr":38886,"type":"DATA"},{"addr":49420,"type":"DATA"}],"xrefs":[{"addr":10363,"type":"CODE"}]},{"offset":10534,"esil":"0,eax,eax,&,==,$z,zf,:=,$p,pf,:=,31,$s,sf,:=,0,cf,:=,0,of,:=","refptr":false,"fcn_addr":10144,"fcn_last":11115,"size":2,"opcode":"test eax, eax","disasm":"test eax, eax","bytes":"85c0","family":"cpu","type":"acmp","reloc":false,"type_num":16,"type2_num":0},{"offset":10536,"esil":"zf,!,?{,10990,rip,=,}","refptr":false,"fcn_addr":10144,"fcn_last":11111,"size":6,"opcode":"jne 0x2aee","disasm":"jne 0x2aee","bytes":"0f85c0010000","family":"cpu","type":"cjmp","reloc":false,"type_num":2147483649,"type2_num":0,"jump":10990,"fail":10542,"refs":[{"addr":10990,"type":"CODE"}]}]},{"offset":10542,"size":26,"jump":10296,"ops":[{"offset":10542,"ptr":49344,"esil":"0x978b,rip,+,[8],rax,=","refptr":true,"fcn_addr":10144,"fcn_last":11110,"size":7,"opcode":"mov rax, qword [rip + 0x978b]","disasm":"mov rax, qword [obj.optarg]","bytes":"488b058b970000","family":"cpu","type":"mov","reloc":false,"type_num":9,"type2_num":0,"refs":[{"addr":38795,"type":"DATA"},{"addr":49344,"type":"DATA"}]},{"offset":10549,"ptr":49420,"val":2,"esil":"2,0x97cd,rip,+,=[4]","refptr":true,"fcn_addr":10144,"fcn_last":11107,"size":10,"opcode":"mov dword [rip + 0x97cd], 2","disasm":"mov dword [obj.operating_mode], 2","bytes":"c705cd97000002000000","family":"cpu","type":"mov","reloc":false,"type_num":9,"type2_num":0,"refs":[{"addr":38861,"type":"DATA"},{"addr":49420,"type":"DATA"}]},{"offset":10559,"esil":"rax,rsp,=[8]","refptr":true,"fcn_addr":10144,"fcn_last":11113,"size":4,"opcode":"mov qword [rsp], rax","disasm":"mov qword [rsp], rax","bytes":"48890424","family":"cpu","type":"mov","reloc":false,"type_num":9,"type2_num":0},{"offset":10563,"esil":"0x2838,rip,=","refptr":false,"fcn_addr":10144,"fcn_last":11112,"size":5,"opcode":"jmp 0x2838","disasm":"jmp case.0x287b.110","bytes":"e9f0feffff","family":"cpu","type":"jmp","reloc":false,"type_num":1,"type2_num":0,"jump":10296,"refs":[{"addr":10296,"type":"CODE"}]}]},{"offset":10576,"size":14,"jump":10600,"fail":10590,"ops":[{"offset":10576,"ptr":49344,"esil":"0x9769,rip,+,[8],rdx,=","refptr":true,"fcn_addr":10144,"fcn_last":11110,"size":7,"opcode":"mov rdx, qword [rip + 0x9769]","disasm":"mov rdx, qword [obj.optarg]","bytes":"488b1569970000","family":"cpu","type":"mov","reloc":false,"type_num":9,"type2_num":0,"flags":["case.0x287b.100"],"refs":[{"addr":38761,"type":"DATA"},{"addr":49344,"type":"DATA"}],"xrefs":[{"addr":10363,"type":"CODE"}]},{"offset":10583,"esil":"rdx,[1],rax,=","refptr":true,"fcn_addr":10144,"fcn_last":11114,"size":3,"opcode":"movzx eax, byte [rdx]","disasm":"movzx eax, byte [rdx]","bytes":"0fb602","family":"cpu","type":"mov","reloc":false,"type_num":9,"type2_num":0},{"offset":10586,"esil":"0,al,al,&,==,$z,zf,:=,$p,pf,:=,7,$s,sf,:=,0,cf,:=,0,of,:=","refptr":false,"fcn_addr":10144,"fcn_last":11115,"size":2,"opcode":"test al, al","disasm":"test al, al","bytes":"84c0","family":"cpu","type":"acmp","reloc":false,"type_num":16,"type2_num":0},{"offset":10588,"esil":"zf,?{,10600,rip,=,}","refptr":false,"fcn_addr":10144,"fcn_last":11115,"size":2,"opcode":"je 0x2968","disasm":"je 0x2968","bytes":"740a","family":"cpu","type":"cjmp","reloc":false,"type_num":2147483649,"type2_num":0,"jump":10600,"fail":10590,"refs":[{"addr":10600,"type":"CODE"}]}]},{"offset":10590,"size":10,"jump":11103,"fail":10600,"ops":[{"offset":10590,"val":0,"esil":"0,0x1,rdx,+,[1],==,$z,zf,:=,8,$b,cf,:=,$p,pf,:=,7,$s,sf,:=,0,0x80,-,!,7,$o,^,of,:=,3,$b,af,:=","refptr":true,"fcn_addr":10144,"fcn_last":11113,"size":4,"opcode":"cmp byte [rdx + 1], 0","disasm":"cmp byte [rdx + 1], 0","bytes":"807a0100","family":"cpu","type":"cmp","reloc":false,"type_num":15,"type2_num":0},{"offset":10594,"esil":"zf,!,?{,11103,rip,=,}","refptr":false,"fcn_addr":10144,"fcn_last":11111,"size":6,"opcode":"jne 0x2b5f","disasm":"jne 0x2b5f","bytes":"0f85f7010000","family":"cpu","type":"cjmp","reloc":false,"type_num":2147483649,"type2_num":0,"jump":11103,"fail":10600,"refs":[{"addr":11103,"type":"CODE"}]}]},{"offset":10600,"size":17,"jump":10296,"ops":[{"offset":10600,"ptr":49417,"esil":"al,0x979b,rip,+,=[1]","refptr":true,"fcn_addr":10144,"fcn_last":11111,"size":6,"opcode":"mov byte [rip + 0x979b], al","disasm":"mov byte [obj.delim], al","bytes":"88059b970000","family":"cpu","type":"mov","reloc":false,"type_num":9,"type2_num":0,"refs":[{"addr":38811,"type":"DATA"},{"addr":49417,"type":"DATA"}],"xrefs":[{"addr":10588,"type":"CODE"}]},{"offset":10606,"val":1,"esil":"1,r15,=","refptr":false,"fcn_addr":10144,"fcn_last":11111,"size":6,"opcode":"mov r15d, 1","disasm":"mov r15d, 1","bytes":"41bf01000000","family":"cpu","type":"mov","reloc":false,"type_num":9,"type2_num":0},{"offset":10612,"esil":"0x2838,rip,=","refptr":false,"fcn_addr":10144,"fcn_last":11112,"size":5,"opcode":"jmp 0x2838","disasm":"jmp case.0x287b.110","bytes":"e9bffeffff","family":"cpu","type":"jmp","reloc":false,"type_num":1,"type2_num":0,"jump":10296,"refs":[{"addr":10296,"type":"CODE"}]}]},{"offset":10624,"size":7,"jump":10697,"fail":10631,"ops":[{"offset":10624,"ptr":4294967165,"val":4294967165,"esil":"4294967165,eax,==,$z,zf,:=,32,$b,cf,:=,$p,pf,:=,31,$s,sf,:=,4294967165,0x80000000,-,!,31,$o,^,of,:=,3,$b,af,:=","refptr":false,"fcn_addr":10144,"fcn_last":11112,"size":5,"opcode":"cmp eax, 0xffffff7d","disasm":"cmp eax, 0xffffff7d","bytes":"3d7dffffff","family":"cpu","type":"cmp","reloc":false,"type_num":15,"type2_num":0,"xrefs":[{"addr":10338,"type":"CODE"}]},{"offset":10629,"esil":"zf,!,?{,10697,rip,=,}","refptr":false,"fcn_addr":10144,"fcn_last":11115,"size":2,"opcode":"jne 0x29c9","disasm":"jne 0x29c9","bytes":"7542","family":"cpu","type":"cjmp","reloc":false,"type_num":2147483649,"type2_num":0,"jump":10697,"fail":10631,"refs":[{"addr":10697,"type":"CODE"}]}]},{"offset":10631,"size":66,"ops":[{"offset":10631,"ptr":33017,"esil":"0x576b,rip,+,rax,=","refptr":true,"fcn_addr":10144,"fcn_last":11110,"size":7,"opcode":"lea rax, [rip + 0x576b]","disasm":"lea rax, str.Jim_Meyering","bytes":"488d056b570000","family":"cpu","type":"lea","reloc":false,"type_num":33,"type2_num":0,"refs":[{"addr":22379,"type":"DATA"},{"addr":33017,"type":"DATA"}]},{"offset":10638,"ptr":0,"val":0,"esil":"0,8,rsp,-,=[8],8,rsp,-=","refptr":false,"fcn_addr":10144,"fcn_last":11115,"size":2,"opcode":"push 0","disasm":"push 0","bytes":"6a00","family":"cpu","type":"push","reloc":false,"type_num":13,"type2_num":0},{"offset":10640,"ptr":49320,"esil":"0x9711,rip,+,[8],rdi,=","refptr":true,"fcn_addr":10144,"fcn_last":11110,"size":7,"opcode":"mov rdi, qword [rip + 0x9711]","disasm":"mov rdi, qword [obj.stdout]","bytes":"488b3d11970000","family":"cpu","type":"mov","reloc":false,"type_num":9,"type2_num":0,"refs":[{"addr":38673,"type":"DATA"},{"addr":49320,"type":"DATA"}]},{"offset":10647,"ptr":32986,"esil":"0x573c,rip,+,r9,=","refptr":true,"fcn_addr":10144,"fcn_last":11110,"size":7,"opcode":"lea r9, [rip + 0x573c]","disasm":"lea r9, str.David_MacKenzie","bytes":"4c8d0d3c570000","family":"cpu","type":"lea","reloc":false,"type_num":33,"type2_num":0,"refs":[{"addr":22332,"type":"DATA"},{"addr":32986,"type":"DATA"}]},{"offset":10654,"esil":"rax,8,rsp,-,=[8],8,rsp,-=","refptr":false,"fcn_addr":10144,"fcn_last":11116,"size":1,"opcode":"push rax","disasm":"push rax","bytes":"50","family":"cpu","type":"rpush","reloc":false,"type_num":268435468,"type2_num":0},{"offset":10655,"ptr":49176,"esil":"0x9672,rip,+,[8],rcx,=","refptr":true,"fcn_addr":10144,"fcn_last":11110,"size":7,"opcode":"mov rcx, qword [rip + 0x9672]","disasm":"mov rcx, qword [obj.Version]","bytes":"488b0d72960000","family":"cpu","type":"mov","reloc":false,"type_num":9,"type2_num":0,"refs":[{"addr":38514,"type":"DATA"},{"addr":49176,"type":"DATA"}]},{"offset":10662,"esil":"eax,rax,^,0xffffffff,&,rax,=,$z,zf,:=,$p,pf,:=,31,$s,sf,:=,0,cf,:=,0,of,:=","refptr":false,"fcn_addr":10144,"fcn_last":11115,"size":2,"opcode":"xor eax, eax","disasm":"xor eax, eax","bytes":"31c0","family":"cpu","type":"xor","reloc":false,"type_num":28,"type2_num":0},{"offset":10664,"ptr":33002,"esil":"0x573b,rip,+,r8,=","refptr":true,"fcn_addr":10144,"fcn_last":11110,"size":7,"opcode":"lea r8, [rip + 0x573b]","disasm":"lea r8, str.David_M._Ihnat","bytes":"4c8d053b570000","family":"cpu","type":"lea","reloc":false,"type_num":33,"type2_num":0,"refs":[{"addr":22331,"type":"DATA"},{"addr":33002,"type":"DATA"}]},{"offset":10671,"ptr":32917,"esil":"0x56df,rip,+,rdx,=","refptr":true,"fcn_addr":10144,"fcn_last":11110,"size":7,"opcode":"lea rdx, [rip + 0x56df]","disasm":"lea rdx, str.GNU_coreutils","bytes":"488d15df560000","family":"cpu","type":"lea","reloc":false,"type_num":33,"type2_num":0,"refs":[{"addr":22239,"type":"DATA"},{"addr":32917,"type":"DATA"}]},{"offset":10678,"ptr":32795,"esil":"0x565e,rip,+,rsi,=","refptr":true,"fcn_addr":10144,"fcn_last":11110,"size":7,"opcode":"lea rsi, [rip + 0x565e]","disasm":"lea rsi, [0x0000801b]","bytes":"488d355e560000","family":"cpu","type":"lea","reloc":false,"type_num":33,"type2_num":0,"refs":[{"addr":22110,"type":"DATA"},{"addr":32795,"type":"DATA"}]},{"offset":10685,"esil":"28432,rip,8,rsp,-=,rsp,=[8],rip,=","refptr":false,"fcn_addr":10144,"fcn_last":11112,"size":5,"opcode":"call 0x6f10","disasm":"call dbg.version_etc","bytes":"e84e450000","family":"cpu","type":"call","reloc":false,"type_num":3,"type2_num":0,"jump":28432,"fail":10690,"refs":[{"addr":28432,"type":"CALL"}]},{"offset":10690,"esil":"edi,rdi,^,0xffffffff,&,rdi,=,$z,zf,:=,$p,pf,:=,31,$s,sf,:=,0,cf,:=,0,of,:=","refptr":false,"fcn_addr":10144,"fcn_last":11115,"size":2,"opcode":"xor edi, edi","disasm":"xor edi, edi","bytes":"31ff","family":"cpu","type":"xor","reloc":false,"type_num":28,"type2_num":0},{"offset":10692,"esil":"9984,rip,8,rsp,-=,rsp,=[8],rip,=","refptr":false,"fcn_addr":10144,"fcn_last":11112,"size":5,"opcode":"call 0x2700","disasm":"call sym.imp.exit","bytes":"e837fdffff","family":"cpu","type":"call","reloc":false,"type_num":3,"type2_num":0,"jump":9984,"fail":10697,"refs":[{"addr":9984,"type":"CALL"}]}]},{"offset":10697,"size":11,"jump":11023,"fail":10708,"ops":[{"offset":10697,"ptr":4294967166,"val":4294967166,"esil":"4294967166,eax,==,$z,zf,:=,32,$b,cf,:=,$p,pf,:=,31,$s,sf,:=,4294967166,0x80000000,-,!,31,$o,^,of,:=,3,$b,af,:=","refptr":false,"fcn_addr":10144,"fcn_last":11112,"size":5,"opcode":"cmp eax, 0xffffff7e","disasm":"cmp eax, 0xffffff7e","bytes":"3d7effffff","family":"cpu","type":"cmp","reloc":false,"type_num":15,"type2_num":0,"xrefs":[{"addr":10629,"type":"CODE"}]},{"offset":10702,"esil":"zf,!,?{,11023,rip,=,}","refptr":false,"fcn_addr":10144,"fcn_last":11111,"size":6,"opcode":"jne 0x2b0f","disasm":"jne case.0x287b.101","bytes":"0f853b010000","family":"cpu","type":"cjmp","reloc":false,"type_num":2147483649,"type2_num":0,"jump":11023,"fail":10708,"refs":[{"addr":11023,"type":"CODE"}]}]},{"offset":10708,"size":7,"jump":10715,"ops":[{"offset":10708,"esil":"edi,rdi,^,0xffffffff,&,rdi,=,$z,zf,:=,$p,pf,:=,31,$s,sf,:=,0,cf,:=,0,of,:=","refptr":false,"fcn_addr":10144,"fcn_last":11115,"size":2,"opcode":"xor edi, edi","disasm":"xor edi, edi","bytes":"31ff","family":"cpu","type":"xor","reloc":false,"type_num":28,"type2_num":0},{"offset":10710,"esil":"13584,rip,8,rsp,-=,rsp,=[8],rip,=","refptr":false,"fcn_addr":10144,"fcn_last":11112,"size":5,"opcode":"call 0x3510","disasm":"call dbg.usage","bytes":"e8350b0000","family":"cpu","type":"call","reloc":false,"type_num":3,"type2_num":0,"jump":13584,"fail":10715,"refs":[{"addr":13584,"type":"CALL"}]}]},{"offset":10715,"size":26,"jump":11002,"fail":10741,"ops":[{"offset":10715,"ptr":49420,"esil":"0x972b,rip,+,[4],rax,=","refptr":true,"fcn_addr":10144,"fcn_last":11111,"size":6,"opcode":"mov eax, dword [rip + 0x972b]","disasm":"mov eax, dword [obj.operating_mode]","bytes":"8b052b970000","family":"cpu","type":"mov","reloc":false,"type_num":9,"type2_num":0,"refs":[{"addr":38699,"type":"DATA"},{"addr":49420,"type":"DATA"}],"xrefs":[{"addr":10318,"type":"CODE"}]},{"offset":10721,"val":5,"esil":"5,rdx,=","refptr":false,"fcn_addr":10144,"fcn_last":11112,"size":5,"opcode":"mov edx, 5","disasm":"mov edx, 5","bytes":"ba05000000","family":"cpu","type":"mov","reloc":false,"type_num":9,"type2_num":0},{"offset":10726,"ptr":35072,"esil":"0x5f13,rip,+,rsi,=","refptr":true,"fcn_addr":10144,"fcn_last":11110,"size":7,"opcode":"lea rsi, [rip + 0x5f13]","disasm":"lea rsi, str.you_must_specify_a_list_of_bytes__characters__or_fields","bytes":"488d35135f0000","family":"cpu","type":"lea","reloc":false,"type_num":33,"type2_num":0,"refs":[{"addr":24339,"type":"DATA"},{"addr":35072,"type":"DATA"}]},{"offset":10733,"esil":"0,eax,eax,&,==,$z,zf,:=,$p,pf,:=,31,$s,sf,:=,0,cf,:=,0,of,:=","refptr":false,"fcn_addr":10144,"fcn_last":11115,"size":2,"opcode":"test eax, eax","disasm":"test eax, eax","bytes":"85c0","family":"cpu","type":"acmp","reloc":false,"type_num":16,"type2_num":0},{"offset":10735,"esil":"zf,?{,11002,rip,=,}","refptr":false,"fcn_addr":10144,"fcn_last":11111,"size":6,"opcode":"je 0x2afa","disasm":"je 0x2afa","bytes":"0f8405010000","family":"cpu","type":"cjmp","reloc":false,"type_num":2147483649,"type2_num":0,"jump":11002,"fail":10741,"refs":[{"addr":11002,"type":"CODE"}]}]},{"offset":10741,"size":11,"jump":10772,"fail":10752,"ops":[{"offset":10741,"ptr":2,"val":2,"esil":"2,eax,==,$z,zf,:=,32,$b,cf,:=,$p,pf,:=,31,$s,sf,:=,2,0x80000000,-,!,31,$o,^,of,:=,3,$b,af,:=","refptr":false,"fcn_addr":10144,"fcn_last":11114,"size":3,"opcode":"cmp eax, 2","disasm":"cmp eax, 2","bytes":"83f802","family":"cpu","type":"cmp","reloc":false,"type_num":15,"type2_num":0,"refs":[{"addr":2,"type":"DATA"}]},{"offset":10744,"esil":"zf,!,al,=","refptr":false,"fcn_addr":10144,"fcn_last":11114,"size":3,"opcode":"setne al","disasm":"setne al","bytes":"0f95c0","family":"cpu","type":"cmov","reloc":false,"type_num":2147483657,"type2_num":0},{"offset":10747,"esil":"0,r15b,r15b,&,==,$z,zf,:=,$p,pf,:=,7,$s,sf,:=,0,cf,:=,0,of,:=","refptr":false,"fcn_addr":10144,"fcn_last":11114,"size":3,"opcode":"test r15b, r15b","disasm":"test r15b, r15b","bytes":"4584ff","family":"cpu","type":"acmp","reloc":false,"type_num":16,"type2_num":0},{"offset":10750,"esil":"zf,?{,10772,rip,=,}","refptr":false,"fcn_addr":10144,"fcn_last":11115,"size":2,"opcode":"je 0x2a14","disasm":"je 0x2a14","bytes":"7414","family":"cpu","type":"cjmp","reloc":false,"type_num":2147483649,"type2_num":0,"jump":10772,"fail":10752,"refs":[{"addr":10772,"type":"CODE"}]}]},{"offset":10752,"size":20,"jump":11002,"fail":10772,"ops":[{"offset":10752,"val":5,"esil":"5,rdx,=","refptr":false,"fcn_addr":10144,"fcn_last":11112,"size":5,"opcode":"mov edx, 5","disasm":"mov edx, 5","bytes":"ba05000000","family":"cpu","type":"mov","reloc":false,"type_num":9,"type2_num":0},{"offset":10757,"ptr":35128,"esil":"0x5f2c,rip,+,rsi,=","refptr":true,"fcn_addr":10144,"fcn_last":11110,"size":7,"opcode":"lea rsi, [rip + 0x5f2c]","disasm":"lea rsi, str.an_input_delimiter_may_be_specified_only_when_operating_on_fields","bytes":"488d352c5f0000","family":"cpu","type":"lea","reloc":false,"type_num":33,"type2_num":0,"refs":[{"addr":24364,"type":"DATA"},{"addr":35128,"type":"DATA"}]},{"offset":10764,"esil":"0,al,al,&,==,$z,zf,:=,$p,pf,:=,7,$s,sf,:=,0,cf,:=,0,of,:=","refptr":false,"fcn_addr":10144,"fcn_last":11115,"size":2,"opcode":"test al, al","disasm":"test al, al","bytes":"84c0","family":"cpu","type":"acmp","reloc":false,"type_num":16,"type2_num":0},{"offset":10766,"esil":"zf,!,?{,11002,rip,=,}","refptr":false,"fcn_addr":10144,"fcn_last":11111,"size":6,"opcode":"jne 0x2afa","disasm":"jne 0x2afa","bytes":"0f85e6000000","family":"cpu","type":"cjmp","reloc":false,"type_num":2147483649,"type2_num":0,"jump":11002,"fail":10772,"refs":[{"addr":11002,"type":"CODE"}]}]},{"offset":10772,"size":26,"jump":11002,"fail":10798,"ops":[{"offset":10772,"esil":"eax,rdx,=","refptr":false,"fcn_addr":10144,"fcn_last":11115,"size":2,"opcode":"mov edx, eax","disasm":"mov edx, eax","bytes":"89c2","family":"cpu","type":"mov","reloc":false,"type_num":9,"type2_num":0,"xrefs":[{"addr":10750,"type":"CODE"}]},{"offset":10774,"ptr":49419,"esil":"0x96ef,rip,+,[1],dl,&=,$z,zf,:=,$p,pf,:=,7,$s,sf,:=,0,cf,:=,0,of,:=","refptr":true,"fcn_addr":10144,"fcn_last":11111,"size":6,"opcode":"and dl, byte [rip + 0x96ef]","disasm":"and dl, byte [obj.suppress_non_delimited]","bytes":"2215ef960000","family":"cpu","type":"and","reloc":false,"type_num":27,"type2_num":0,"refs":[{"addr":38639,"type":"DATA"},{"addr":49419,"type":"DATA"}]},{"offset":10780,"ptr":35200,"esil":"0x5f5d,rip,+,rsi,=","refptr":true,"fcn_addr":10144,"fcn_last":11110,"size":7,"opcode":"lea rsi, [rip + 0x5f5d]","disasm":"lea rsi, str.suppressing_non_delimited_lines_makes_sense_n_tonly_when_operating_on_fields","bytes":"488d355d5f0000","family":"cpu","type":"lea","reloc":false,"type_num":33,"type2_num":0,"refs":[{"addr":24413,"type":"DATA"},{"addr":35200,"type":"DATA"}]},{"offset":10787,"val":5,"esil":"5,rdx,=","refptr":false,"fcn_addr":10144,"fcn_last":11112,"size":5,"opcode":"mov edx, 5","disasm":"mov edx, 5","bytes":"ba05000000","family":"cpu","type":"mov","reloc":false,"type_num":9,"type2_num":0},{"offset":10792,"esil":"zf,!,?{,11002,rip,=,}","refptr":false,"fcn_addr":10144,"fcn_last":11111,"size":6,"opcode":"jne 0x2afa","disasm":"jne 0x2afa","bytes":"0f85cc000000","family":"cpu","type":"cjmp","reloc":false,"type_num":2147483649,"type2_num":0,"jump":11002,"fail":10798,"refs":[{"addr":11002,"type":"CODE"}]}]},{"offset":10798,"size":31,"jump":10836,"fail":10829,"ops":[{"offset":10798,"ptr":49418,"esil":"0x96d5,rip,+,[1],rsi,=","refptr":true,"fcn_addr":10144,"fcn_last":11110,"size":7,"opcode":"movzx esi, byte [rip + 0x96d5]","disasm":"movzx esi, byte [obj.complement]","bytes":"0fb635d5960000","family":"cpu","type":"mov","reloc":false,"type_num":9,"type2_num":0,"refs":[{"addr":38613,"type":"DATA"},{"addr":49418,"type":"DATA"}]},{"offset":10805,"esil":"al,rax,=","refptr":false,"fcn_addr":10144,"fcn_last":11114,"size":3,"opcode":"movzx eax, al","disasm":"movzx eax, al","bytes":"0fb6c0","family":"cpu","type":"mov","reloc":false,"type_num":9,"type2_num":0},{"offset":10808,"esil":"rsp,[8],rdi,=","refptr":true,"fcn_addr":10144,"fcn_last":11113,"size":4,"opcode":"mov rdi, qword [rsp]","disasm":"mov rdi, qword [rsp]","bytes":"488b3c24","family":"cpu","type":"mov","reloc":false,"type_num":9,"type2_num":0},{"offset":10812,"esil":"0,2,!,!,?{,1,2,-,eax,<<,0x80000000,&,!,!,^,},2,eax,<<=,$z,zf,:=,$p,pf,:=,31,$s,sf,:=,cf,=","refptr":false,"fcn_addr":10144,"fcn_last":11114,"size":3,"opcode":"shl eax, 2","disasm":"shl eax, 2","bytes":"c1e002","family":"cpu","type":"shl","reloc":false,"type_num":23,"type2_num":0},{"offset":10815,"esil":"esi,esi,+=,31,$o,of,:=,31,$s,sf,:=,$z,zf,:=,31,$c,cf,:=,$p,pf,:=,3,$c,af,:=","refptr":false,"fcn_addr":10144,"fcn_last":11115,"size":2,"opcode":"add esi, esi","disasm":"add esi, esi","bytes":"01f6","family":"cpu","type":"add","reloc":false,"type_num":17,"type2_num":0},{"offset":10817,"esil":"eax,esi,|=,31,$s,sf,:=,$z,zf,:=,$p,pf,:=,0,of,:=,0,cf,:=","refptr":false,"fcn_addr":10144,"fcn_last":11115,"size":2,"opcode":"or esi, eax","disasm":"or esi, eax","bytes":"09c6","family":"cpu","type":"or","reloc":false,"type_num":26,"type2_num":0},{"offset":10819,"esil":"14912,rip,8,rsp,-=,rsp,=[8],rip,=","refptr":false,"fcn_addr":10144,"fcn_last":11112,"size":5,"opcode":"call 0x3a40","disasm":"call dbg.set_fields","bytes":"e8f80f0000","family":"cpu","type":"call","reloc":false,"type_num":3,"type2_num":0,"jump":14912,"fail":10824,"refs":[{"addr":14912,"type":"CALL"}]},{"offset":10824,"esil":"0,r15b,r15b,&,==,$z,zf,:=,$p,pf,:=,7,$s,sf,:=,0,cf,:=,0,of,:=","refptr":false,"fcn_addr":10144,"fcn_last":11114,"size":3,"opcode":"test r15b, r15b","disasm":"test r15b, r15b","bytes":"4584ff","family":"cpu","type":"acmp","reloc":false,"type_num":16,"type2_num":0},{"offset":10827,"esil":"zf,!,?{,10836,rip,=,}","refptr":false,"fcn_addr":10144,"fcn_last":11115,"size":2,"opcode":"jne 0x2a54","disasm":"jne 0x2a54","bytes":"7507","family":"cpu","type":"cjmp","reloc":false,"type_num":2147483649,"type2_num":0,"jump":10836,"fail":10829,"refs":[{"addr":10836,"type":"CODE"}]}]},{"offset":10829,"size":7,"jump":10836,"ops":[{"offset":10829,"ptr":49417,"val":9,"esil":"9,0x96b5,rip,+,=[1]","refptr":true,"fcn_addr":10144,"fcn_last":11110,"size":7,"opcode":"mov byte [rip + 0x96b5], 9","disasm":"mov byte [obj.delim], 9","bytes":"c605b596000009","family":"cpu","type":"mov","reloc":false,"type_num":9,"type2_num":0,"refs":[{"addr":38581,"type":"DATA"},{"addr":49417,"type":"DATA"}]}]},{"offset":10836,"size":14,"jump":11033,"fail":10850,"ops":[{"offset":10836,"ptr":49400,"val":0,"esil":"0,0x969c,rip,+,[8],==,$z,zf,:=,64,$b,cf,:=,$p,pf,:=,63,$s,sf,:=,0,0x8000000000000000,-,!,63,$o,^,of,:=,3,$b,af,:=","refptr":true,"fcn_addr":10144,"fcn_last":11109,"size":8,"opcode":"cmp qword [rip + 0x969c], 0","disasm":"cmp qword [obj.output_delimiter_string], 0","bytes":"48833d9c96000000","family":"cpu","type":"cmp","reloc":false,"type_num":15,"type2_num":0,"refs":[{"addr":38556,"type":"DATA"},{"addr":49400,"type":"DATA"}],"xrefs":[{"addr":10827,"type":"CODE"}]},{"offset":10844,"esil":"zf,?{,11033,rip,=,}","refptr":false,"fcn_addr":10144,"fcn_last":11111,"size":6,"opcode":"je 0x2b19","disasm":"je 0x2b19","bytes":"0f84b7000000","family":"cpu","type":"cjmp","reloc":false,"type_num":2147483649,"type2_num":0,"jump":11033,"fail":10850,"refs":[{"addr":11033,"type":"CODE"}]}]},{"offset":10850,"size":14,"jump":11083,"fail":10864,"ops":[{"offset":10850,"ptr":49336,"esil":"0x9650,rip,+,[4],rax,=","refptr":true,"fcn_addr":10144,"fcn_last":11111,"size":6,"opcode":"mov eax, dword [rip + 0x9650]","disasm":"mov eax, dword [obj.optind]","bytes":"8b0550960000","family":"cpu","type":"mov","reloc":false,"type_num":9,"type2_num":0,"refs":[{"addr":38480,"type":"DATA"},{"addr":49336,"type":"DATA"}],"xrefs":[{"addr":11078,"type":"CODE"}]},{"offset":10856,"esil":"ebp,eax,==,$z,zf,:=,32,$b,cf,:=,$p,pf,:=,31,$s,sf,:=,ebp,0x80000000,-,!,31,$o,^,of,:=,3,$b,af,:=","refptr":false,"fcn_addr":10144,"fcn_last":11115,"size":2,"opcode":"cmp eax, ebp","disasm":"cmp eax, ebp","bytes":"39e8","family":"cpu","type":"cmp","reloc":false,"type_num":15,"type2_num":0},{"offset":10858,"esil":"zf,?{,11083,rip,=,}","refptr":false,"fcn_addr":10144,"fcn_last":11111,"size":6,"opcode":"je 0x2b4b","disasm":"je 0x2b4b","bytes":"0f84db000000","family":"cpu","type":"cjmp","reloc":false,"type_num":2147483649,"type2_num":0,"jump":11083,"fail":10864,"refs":[{"addr":11083,"type":"CODE"}]}]},{"offset":10864,"size":8,"jump":10913,"fail":10872,"ops":[{"offset":10864,"val":1,"esil":"1,r12,=","refptr":false,"fcn_addr":10144,"fcn_last":11111,"size":6,"opcode":"mov r12d, 1","disasm":"mov r12d, 1","bytes":"41bc01000000","family":"cpu","type":"mov","reloc":false,"type_num":9,"type2_num":0},{"offset":10870,"esil":"of,!,sf,^,?{,10913,rip,=,}","refptr":false,"fcn_addr":10144,"fcn_last":11115,"size":2,"opcode":"jge 0x2aa1","disasm":"jge 0x2aa1","bytes":"7d29","family":"cpu","type":"cjmp","reloc":false,"type_num":2147483649,"type2_num":0,"jump":10913,"fail":10872,"refs":[{"addr":10913,"type":"CODE"}]}]},{"offset":10872,"size":8,"jump":10880,"ops":[{"offset":10872,"esil":",","refptr":false,"fcn_addr":10144,"fcn_last":11109,"size":8,"opcode":"nop dword [rax + rax]","disasm":"nop dword [rax + rax]","bytes":"0f1f840000000000","family":"cpu","type":"nop","reloc":false,"type_num":8,"type2_num":0}]},{"offset":10880,"size":33,"jump":10880,"fail":10913,"ops":[{"offset":10880,"esil":"eax,rax,=,31,rax,>>,?{,0xffffffff00000000,rax,|=,}","refptr":false,"fcn_addr":10144,"fcn_last":11115,"size":2,"opcode":"cdqe","disasm":"cdqe","bytes":"4898","family":"cpu","type":"null","reloc":false,"type_num":0,"type2_num":0,"xrefs":[{"addr":10911,"type":"CODE"}]},{"offset":10882,"esil":"rax,8,*,rbx,+,[8],rdi,=","refptr":true,"fcn_addr":10144,"fcn_last":11113,"size":4,"opcode":"mov rdi, qword [rbx + rax*8]","disasm":"mov rdi, qword [rbx + rax*8]","bytes":"488b3cc3","family":"cpu","type":"mov","reloc":false,"type_num":9,"type2_num":0},{"offset":10886,"esil":"11360,rip,8,rsp,-=,rsp,=[8],rip,=","refptr":false,"fcn_addr":10144,"fcn_last":11112,"size":5,"opcode":"call 0x2c60","disasm":"call dbg.cut_file","bytes":"e8d5010000","family":"cpu","type":"call","reloc":false,"type_num":3,"type2_num":0,"jump":11360,"fail":10891,"refs":[{"addr":11360,"type":"CALL"}]},{"offset":10891,"esil":"eax,r12,&,0xffffffff,&,r12,=,$z,zf,:=,$p,pf,:=,31,$s,sf,:=,0,cf,:=,0,of,:=","refptr":false,"fcn_addr":10144,"fcn_last":11114,"size":3,"opcode":"and r12d, eax","disasm":"and r12d, eax","bytes":"4121c4","family":"cpu","type":"and","reloc":false,"type_num":27,"type2_num":0},{"offset":10894,"ptr":49336,"esil":"0x9624,rip,+,[4],rax,=","refptr":true,"fcn_addr":10144,"fcn_last":11111,"size":6,"opcode":"mov eax, dword [rip + 0x9624]","disasm":"mov eax, dword [obj.optind]","bytes":"8b0524960000","family":"cpu","type":"mov","reloc":false,"type_num":9,"type2_num":0,"refs":[{"addr":38436,"type":"DATA"},{"addr":49336,"type":"DATA"}]},{"offset":10900,"val":1,"esil":"1,eax,+=,31,$o,of,:=,31,$s,sf,:=,$z,zf,:=,31,$c,cf,:=,$p,pf,:=,3,$c,af,:=","refptr":false,"fcn_addr":10144,"fcn_last":11114,"size":3,"opcode":"add eax, 1","disasm":"add eax, 1","bytes":"83c001","family":"cpu","type":"add","reloc":false,"type_num":17,"type2_num":0},{"offset":10903,"ptr":49336,"esil":"eax,0x961b,rip,+,=[4]","refptr":true,"fcn_addr":10144,"fcn_last":11111,"size":6,"opcode":"mov dword [rip + 0x961b], eax","disasm":"mov dword [obj.optind], eax","bytes":"89051b960000","family":"cpu","type":"mov","reloc":false,"type_num":9,"type2_num":0,"refs":[{"addr":38427,"type":"DATA"},{"addr":49336,"type":"DATA"}]},{"offset":10909,"esil":"ebp,eax,==,$z,zf,:=,32,$b,cf,:=,$p,pf,:=,31,$s,sf,:=,ebp,0x80000000,-,!,31,$o,^,of,:=,3,$b,af,:=","refptr":false,"fcn_addr":10144,"fcn_last":11115,"size":2,"opcode":"cmp eax, ebp","disasm":"cmp eax, ebp","bytes":"39e8","family":"cpu","type":"cmp","reloc":false,"type_num":15,"type2_num":0},{"offset":10911,"esil":"of,sf,^,?{,10880,rip,=,}","refptr":false,"fcn_addr":10144,"fcn_last":11115,"size":2,"opcode":"jl 0x2a80","disasm":"jl 0x2a80","bytes":"7cdf","family":"cpu","type":"cjmp","reloc":false,"type_num":2147483649,"type2_num":0,"jump":10880,"fail":10913,"refs":[{"addr":10880,"type":"CODE"}]}]},{"offset":10913,"size":9,"jump":10945,"fail":10922,"ops":[{"offset":10913,"ptr":49394,"val":0,"esil":"0,0x964a,rip,+,[1],==,$z,zf,:=,8,$b,cf,:=,$p,pf,:=,7,$s,sf,:=,0,0x80,-,!,7,$o,^,of,:=,3,$b,af,:=","refptr":true,"fcn_addr":10144,"fcn_last":11110,"size":7,"opcode":"cmp byte [rip + 0x964a], 0","disasm":"cmp byte [obj.have_read_stdin], 0","bytes":"803d4a96000000","family":"cpu","type":"cmp","reloc":false,"type_num":15,"type2_num":0,"refs":[{"addr":38474,"type":"DATA"},{"addr":49394,"type":"DATA"}],"xrefs":[{"addr":10870,"type":"CODE"},{"addr":11098,"type":"CODE"}]},{"offset":10920,"esil":"zf,!,?{,10945,rip,=,}","refptr":false,"fcn_addr":10144,"fcn_last":11115,"size":2,"opcode":"jne 0x2ac1","disasm":"jne 0x2ac1","bytes":"7517","family":"cpu","type":"cjmp","reloc":false,"type_num":2147483649,"type2_num":0,"jump":10945,"fail":10922,"refs":[{"addr":10945,"type":"CODE"}]}]},{"offset":10922,"size":23,"ops":[{"offset":10922,"val":24,"esil":"24,rsp,+=,63,$o,of,:=,63,$s,sf,:=,$z,zf,:=,63,$c,cf,:=,$p,pf,:=,3,$c,af,:=","refptr":false,"fcn_addr":10144,"fcn_last":11113,"size":4,"opcode":"add rsp, 0x18","disasm":"add rsp, 0x18","bytes":"4883c418","family":"cpu","type":"add","reloc":false,"type_num":17,"type2_num":0,"xrefs":[{"addr":10960,"type":"CODE"},{"addr":10988,"type":"CODE"}]},{"offset":10926,"val":1,"esil":"1,r12,^,0xffffffff,&,r12,=,$z,zf,:=,$p,pf,:=,31,$s,sf,:=,0,cf,:=,0,of,:=","refptr":false,"fcn_addr":10144,"fcn_last":11113,"size":4,"opcode":"xor r12d, 1","disasm":"xor r12d, 1","bytes":"4183f401","family":"cpu","type":"xor","reloc":false,"type_num":28,"type2_num":0},{"offset":10930,"esil":"rsp,[8],rbx,=,8,rsp,+=","refptr":false,"fcn_addr":10144,"fcn_last":11116,"size":1,"opcode":"pop rbx","disasm":"pop rbx","bytes":"5b","family":"cpu","type":"pop","reloc":false,"type_num":14,"type2_num":0},{"offset":10931,"esil":"r12b,rax,=","refptr":false,"fcn_addr":10144,"fcn_last":11113,"size":4,"opcode":"movzx eax, r12b","disasm":"movzx eax, r12b","bytes":"410fb6c4","family":"cpu","type":"mov","reloc":false,"type_num":9,"type2_num":0},{"offset":10935,"esil":"rsp,[8],rbp,=,8,rsp,+=","refptr":false,"fcn_addr":10144,"fcn_last":11116,"size":1,"opcode":"pop rbp","disasm":"pop rbp","bytes":"5d","family":"cpu","type":"pop","reloc":false,"type_num":14,"type2_num":0},{"offset":10936,"esil":"rsp,[8],r12,=,8,rsp,+=","refptr":false,"fcn_addr":10144,"fcn_last":11115,"size":2,"opcode":"pop r12","disasm":"pop r12","bytes":"415c","family":"cpu","type":"pop","reloc":false,"type_num":14,"type2_num":0},{"offset":10938,"esil":"rsp,[8],r13,=,8,rsp,+=","refptr":false,"fcn_addr":10144,"fcn_last":11115,"size":2,"opcode":"pop r13","disasm":"pop r13","bytes":"415d","family":"cpu","type":"pop","reloc":false,"type_num":14,"type2_num":0},{"offset":10940,"esil":"rsp,[8],r14,=,8,rsp,+=","refptr":false,"fcn_addr":10144,"fcn_last":11115,"size":2,"opcode":"pop r14","disasm":"pop r14","bytes":"415e","family":"cpu","type":"pop","reloc":false,"type_num":14,"type2_num":0},{"offset":10942,"esil":"rsp,[8],r15,=,8,rsp,+=","refptr":false,"fcn_addr":10144,"fcn_last":11115,"size":2,"opcode":"pop r15","disasm":"pop r15","bytes":"415f","family":"cpu","type":"pop","reloc":false,"type_num":14,"type2_num":0},{"offset":10944,"esil":"rsp,[8],rip,=,8,rsp,+=","refptr":false,"fcn_addr":10144,"fcn_last":11116,"size":1,"opcode":"ret","disasm":"ret","bytes":"c3","family":"cpu","type":"ret","reloc":false,"type_num":5,"type2_num":0}]},{"offset":10945,"size":17,"jump":10922,"fail":10962,"ops":[{"offset":10945,"ptr":49328,"esil":"0x95e8,rip,+,[8],rdi,=","refptr":true,"fcn_addr":10144,"fcn_last":11110,"size":7,"opcode":"mov rdi, qword [rip + 0x95e8]","disasm":"mov rdi, qword [obj.stdin]","bytes":"488b3de8950000","family":"cpu","type":"mov","reloc":false,"type_num":9,"type2_num":0,"refs":[{"addr":38376,"type":"DATA"},{"addr":49328,"type":"DATA"}],"xrefs":[{"addr":10920,"type":"CODE"}]},{"offset":10952,"esil":"30272,rip,8,rsp,-=,rsp,=[8],rip,=","refptr":false,"fcn_addr":10144,"fcn_last":11112,"size":5,"opcode":"call 0x7640","disasm":"call dbg.rpl_fclose","bytes":"e8734b0000","family":"cpu","type":"call","reloc":false,"type_num":3,"type2_num":0,"jump":30272,"fail":10957,"refs":[{"addr":30272,"type":"CALL"}]},{"offset":10957,"val":1,"esil":"1,eax,+=,31,$o,of,:=,31,$s,sf,:=,$z,zf,:=,31,$c,cf,:=,$p,pf,:=,3,$c,af,:=","refptr":false,"fcn_addr":10144,"fcn_last":11114,"size":3,"opcode":"add eax, 1","disasm":"add eax, 1","bytes":"83c001","family":"cpu","type":"add","reloc":false,"type_num":17,"type2_num":0},{"offset":10960,"esil":"zf,!,?{,10922,rip,=,}","refptr":false,"fcn_addr":10144,"fcn_last":11115,"size":2,"opcode":"jne 0x2aaa","disasm":"jne 0x2aaa","bytes":"75d8","family":"cpu","type":"cjmp","reloc":false,"type_num":2147483649,"type2_num":0,"jump":10922,"fail":10962,"refs":[{"addr":10922,"type":"CODE"}]}]},{"offset":10962,"size":28,"jump":10922,"ops":[{"offset":10962,"esil":"9216,rip,8,rsp,-=,rsp,=[8],rip,=","refptr":false,"fcn_addr":10144,"fcn_last":11112,"size":5,"opcode":"call 0x2400","disasm":"call sym.imp.__errno_location","bytes":"e829f9ffff","family":"cpu","type":"call","reloc":false,"type_num":3,"type2_num":0,"jump":9216,"fail":10967,"refs":[{"addr":9216,"type":"CALL"}]},{"offset":10967,"ptr":33042,"esil":"0x5634,rip,+,rdx,=","refptr":true,"fcn_addr":10144,"fcn_last":11110,"size":7,"opcode":"lea rdx, [rip + 0x5634]","disasm":"lea rdx, [0x00008112]","bytes":"488d1534560000","family":"cpu","type":"lea","reloc":false,"type_num":33,"type2_num":0,"refs":[{"addr":22068,"type":"DATA"},{"addr":33042,"type":"DATA"}]},{"offset":10974,"esil":"edi,rdi,^,0xffffffff,&,rdi,=,$z,zf,:=,$p,pf,:=,31,$s,sf,:=,0,cf,:=,0,of,:=","refptr":false,"fcn_addr":10144,"fcn_last":11115,"size":2,"opcode":"xor edi, edi","disasm":"xor edi, edi","bytes":"31ff","family":"cpu","type":"xor","reloc":false,"type_num":28,"type2_num":0},{"offset":10976,"esil":"r12d,r12,^,0xffffffff,&,r12,=,$z,zf,:=,$p,pf,:=,31,$s,sf,:=,0,cf,:=,0,of,:=","refptr":false,"fcn_addr":10144,"fcn_last":11114,"size":3,"opcode":"xor r12d, r12d","disasm":"xor r12d, r12d","bytes":"4531e4","family":"cpu","type":"xor","reloc":false,"type_num":28,"type2_num":0},{"offset":10979,"esil":"rax,[4],rsi,=","refptr":true,"fcn_addr":10144,"fcn_last":11115,"size":2,"opcode":"mov esi, dword [rax]","disasm":"mov esi, dword [rax]","bytes":"8b30","family":"cpu","type":"mov","reloc":false,"type_num":9,"type2_num":0},{"offset":10981,"esil":"eax,rax,^,0xffffffff,&,rax,=,$z,zf,:=,$p,pf,:=,31,$s,sf,:=,0,cf,:=,0,of,:=","refptr":false,"fcn_addr":10144,"fcn_last":11115,"size":2,"opcode":"xor eax, eax","disasm":"xor eax, eax","bytes":"31c0","family":"cpu","type":"xor","reloc":false,"type_num":28,"type2_num":0},{"offset":10983,"esil":"9920,rip,8,rsp,-=,rsp,=[8],rip,=","refptr":false,"fcn_addr":10144,"fcn_last":11112,"size":5,"opcode":"call 0x26c0","disasm":"call sym.imp.error","bytes":"e8d4fbffff","family":"cpu","type":"call","reloc":false,"type_num":3,"type2_num":0,"jump":9920,"fail":10988,"refs":[{"addr":9920,"type":"CALL"}]},{"offset":10988,"esil":"0x2aaa,rip,=","refptr":false,"fcn_addr":10144,"fcn_last":11115,"size":2,"opcode":"jmp 0x2aaa","disasm":"jmp 0x2aaa","bytes":"ebbc","family":"cpu","type":"jmp","reloc":false,"type_num":1,"type2_num":0,"jump":10922,"refs":[{"addr":10922,"type":"CODE"}]}]},{"offset":10990,"size":12,"jump":11002,"ops":[{"offset":10990,"val":5,"esil":"5,rdx,=","refptr":false,"fcn_addr":10144,"fcn_last":11112,"size":5,"opcode":"mov edx, 5","disasm":"mov edx, 5","bytes":"ba05000000","family":"cpu","type":"mov","reloc":false,"type_num":9,"type2_num":0,"xrefs":[{"addr":10376,"type":"CODE"},{"addr":10536,"type":"CODE"}]},{"offset":10995,"ptr":34984,"esil":"0x5dae,rip,+,rsi,=","refptr":true,"fcn_addr":10144,"fcn_last":11110,"size":7,"opcode":"lea rsi, [rip + 0x5dae]","disasm":"lea rsi, str.only_one_type_of_list_may_be_specified","bytes":"488d35ae5d0000","family":"cpu","type":"lea","reloc":false,"type_num":33,"type2_num":0,"refs":[{"addr":23982,"type":"DATA"},{"addr":34984,"type":"DATA"}]}]},{"offset":11002,"size":21,"jump":11023,"ops":[{"offset":11002,"esil":"edi,rdi,^,0xffffffff,&,rdi,=,$z,zf,:=,$p,pf,:=,31,$s,sf,:=,0,cf,:=,0,of,:=","refptr":false,"fcn_addr":10144,"fcn_last":11115,"size":2,"opcode":"xor edi, edi","disasm":"xor edi, edi","bytes":"31ff","family":"cpu","type":"xor","reloc":false,"type_num":28,"type2_num":0,"xrefs":[{"addr":10735,"type":"CODE"},{"addr":10766,"type":"CODE"},{"addr":10792,"type":"CODE"},{"addr":11115,"type":"CODE"}]},{"offset":11004,"esil":"9392,rip,8,rsp,-=,rsp,=[8],rip,=","refptr":false,"fcn_addr":10144,"fcn_last":11112,"size":5,"opcode":"call 0x24b0","disasm":"call sym.imp.dcgettext","bytes":"e8aff9ffff","family":"cpu","type":"call","reloc":false,"type_num":3,"type2_num":0,"jump":9392,"fail":11009,"refs":[{"addr":9392,"type":"CALL"}]},{"offset":11009,"esil":"esi,rsi,^,0xffffffff,&,rsi,=,$z,zf,:=,$p,pf,:=,31,$s,sf,:=,0,cf,:=,0,of,:=","refptr":false,"fcn_addr":10144,"fcn_last":11115,"size":2,"opcode":"xor esi, esi","disasm":"xor esi, esi","bytes":"31f6","family":"cpu","type":"xor","reloc":false,"type_num":28,"type2_num":0},{"offset":11011,"esil":"edi,rdi,^,0xffffffff,&,rdi,=,$z,zf,:=,$p,pf,:=,31,$s,sf,:=,0,cf,:=,0,of,:=","refptr":false,"fcn_addr":10144,"fcn_last":11115,"size":2,"opcode":"xor edi, edi","disasm":"xor edi, edi","bytes":"31ff","family":"cpu","type":"xor","reloc":false,"type_num":28,"type2_num":0},{"offset":11013,"esil":"rax,rdx,=","refptr":false,"fcn_addr":10144,"fcn_last":11114,"size":3,"opcode":"mov rdx, rax","disasm":"mov rdx, rax","bytes":"4889c2","family":"cpu","type":"mov","reloc":false,"type_num":9,"type2_num":0},{"offset":11016,"esil":"eax,rax,^,0xffffffff,&,rax,=,$z,zf,:=,$p,pf,:=,31,$s,sf,:=,0,cf,:=,0,of,:=","refptr":false,"fcn_addr":10144,"fcn_last":11115,"size":2,"opcode":"xor eax, eax","disasm":"xor eax, eax","bytes":"31c0","family":"cpu","type":"xor","reloc":false,"type_num":28,"type2_num":0},{"offset":11018,"esil":"9920,rip,8,rsp,-=,rsp,=[8],rip,=","refptr":false,"fcn_addr":10144,"fcn_last":11112,"size":5,"opcode":"call 0x26c0","disasm":"call sym.imp.error","bytes":"e8b1fbffff","family":"cpu","type":"call","reloc":false,"type_num":3,"type2_num":0,"jump":9920,"fail":11023,"refs":[{"addr":9920,"type":"CALL"}]}]},{"offset":11023,"size":10,"jump":11033,"ops":[{"offset":11023,"val":1,"esil":"1,rdi,=","refptr":false,"fcn_addr":10144,"fcn_last":11112,"size":5,"opcode":"mov edi, 1","disasm":"mov edi, 1","bytes":"bf01000000","family":"cpu","type":"mov","reloc":false,"type_num":9,"type2_num":0,"flags":["case.0x287b.101","case.0x287b.103","case.0x287b.104","case.0x287b.105","case.0x287b.106","case.0x287b.107","case.0x287b.108","case.0x287b.109","case.0x287b.111","case.0x287b.112","case.0x287b.113","case.0x287b.114","case.0x287b.116","case.0x287b.117","case.0x287b.118","case.0x287b.119","case.0x287b.120","case.0x287b.121","case.0x287b.123","case.0x287b.124","case.0x287b.125","case.0x287b.126","case.0x287b.127","case.default.0x287b"],"xrefs":[{"addr":10329,"type":"CODE"},{"addr":10350,"type":"CODE"},{"addr":10363,"type":"CODE"},{"addr":10702,"type":"CODE"}]},{"offset":11028,"esil":"13584,rip,8,rsp,-=,rsp,=[8],rip,=","refptr":false,"fcn_addr":10144,"fcn_last":11112,"size":5,"opcode":"call 0x3510","disasm":"call dbg.usage","bytes":"e8f7090000","family":"cpu","type":"call","reloc":false,"type_num":3,"type2_num":0,"jump":13584,"fail":11033,"refs":[{"addr":13584,"type":"CALL"}]}]},{"offset":11033,"size":50,"jump":10850,"ops":[{"offset":11033,"ptr":49417,"esil":"0x95e9,rip,+,[1],rax,=","refptr":true,"fcn_addr":10144,"fcn_last":11110,"size":7,"opcode":"movzx eax, byte [rip + 0x95e9]","disasm":"movzx eax, byte [obj.delim]","bytes":"0fb605e9950000","family":"cpu","type":"mov","reloc":false,"type_num":9,"type2_num":0,"refs":[{"addr":38377,"type":"DATA"},{"addr":49417,"type":"DATA"}],"xrefs":[{"addr":10844,"type":"CODE"}]},{"offset":11040,"ptr":49393,"val":0,"esil":"0,0x95ca,rip,+,=[1]","refptr":true,"fcn_addr":10144,"fcn_last":11110,"size":7,"opcode":"mov byte [rip + 0x95ca], 0","disasm":"mov byte [0x0000c0f1], 0","bytes":"c605ca95000000","family":"cpu","type":"mov","reloc":false,"type_num":9,"type2_num":0,"refs":[{"addr":38346,"type":"DATA"},{"addr":49393,"type":"DATA"}]},{"offset":11047,"ptr":49408,"val":1,"esil":"1,0x95ce,rip,+,=[8]","refptr":true,"fcn_addr":10144,"fcn_last":11106,"size":11,"opcode":"mov qword [rip + 0x95ce], 1","disasm":"mov qword [obj.output_delimiter_length], 1","bytes":"48c705ce95000001000000","family":"cpu","type":"mov","reloc":false,"type_num":9,"type2_num":0,"refs":[{"addr":38350,"type":"DATA"},{"addr":49408,"type":"DATA"}]},{"offset":11058,"ptr":49392,"esil":"al,0x95b8,rip,+,=[1]","refptr":true,"fcn_addr":10144,"fcn_last":11111,"size":6,"opcode":"mov byte [rip + 0x95b8], al","disasm":"mov byte [0x0000c0f0], al","bytes":"8805b8950000","family":"cpu","type":"mov","reloc":false,"type_num":9,"type2_num":0,"refs":[{"addr":38328,"type":"DATA"},{"addr":49392,"type":"DATA"}]},{"offset":11064,"ptr":49392,"esil":"0x95b1,rip,+,rax,=","refptr":true,"fcn_addr":10144,"fcn_last":11110,"size":7,"opcode":"lea rax, [rip + 0x95b1]","disasm":"lea rax, [0x0000c0f0]","bytes":"488d05b1950000","family":"cpu","type":"lea","reloc":false,"type_num":33,"type2_num":0,"refs":[{"addr":38321,"type":"DATA"},{"addr":49392,"type":"DATA"}]},{"offset":11071,"ptr":49400,"esil":"rax,0x95b2,rip,+,=[8]","refptr":true,"fcn_addr":10144,"fcn_last":11110,"size":7,"opcode":"mov qword [rip + 0x95b2], rax","disasm":"mov qword [obj.output_delimiter_string], rax","bytes":"488905b2950000","family":"cpu","type":"mov","reloc":false,"type_num":9,"type2_num":0,"refs":[{"addr":38322,"type":"DATA"},{"addr":49400,"type":"DATA"}]},{"offset":11078,"esil":"0x2a62,rip,=","refptr":false,"fcn_addr":10144,"fcn_last":11112,"size":5,"opcode":"jmp 0x2a62","disasm":"jmp 0x2a62","bytes":"e917ffffff","family":"cpu","type":"jmp","reloc":false,"type_num":1,"type2_num":0,"jump":10850,"refs":[{"addr":10850,"type":"CODE"}]}]},{"offset":11083,"size":20,"jump":10913,"ops":[{"offset":11083,"ptr":33042,"esil":"0x55c0,rip,+,rdi,=","refptr":true,"fcn_addr":10144,"fcn_last":11110,"size":7,"opcode":"lea rdi, [rip + 0x55c0]","disasm":"lea rdi, [0x00008112]","bytes":"488d3dc0550000","family":"cpu","type":"lea","reloc":false,"type_num":33,"type2_num":0,"refs":[{"addr":21952,"type":"DATA"},{"addr":33042,"type":"DATA"}],"xrefs":[{"addr":10858,"type":"CODE"}]},{"offset":11090,"esil":"11360,rip,8,rsp,-=,rsp,=[8],rip,=","refptr":false,"fcn_addr":10144,"fcn_last":11112,"size":5,"opcode":"call 0x2c60","disasm":"call dbg.cut_file","bytes":"e809010000","family":"cpu","type":"call","reloc":false,"type_num":3,"type2_num":0,"jump":11360,"fail":11095,"refs":[{"addr":11360,"type":"CALL"}]},{"offset":11095,"esil":"eax,r12,=","refptr":false,"fcn_addr":10144,"fcn_last":11114,"size":3,"opcode":"mov r12d, eax","disasm":"mov r12d, eax","bytes":"4189c4","family":"cpu","type":"mov","reloc":false,"type_num":9,"type2_num":0},{"offset":11098,"esil":"0x2aa1,rip,=","refptr":false,"fcn_addr":10144,"fcn_last":11112,"size":5,"opcode":"jmp 0x2aa1","disasm":"jmp 0x2aa1","bytes":"e942ffffff","family":"cpu","type":"jmp","reloc":false,"type_num":1,"type2_num":0,"jump":10913,"refs":[{"addr":10913,"type":"CODE"}]}]},{"offset":11103,"size":14,"jump":11002,"ops":[{"offset":11103,"val":5,"esil":"5,rdx,=","refptr":false,"fcn_addr":10144,"fcn_last":11112,"size":5,"opcode":"mov edx, 5","disasm":"mov edx, 5","bytes":"ba05000000","family":"cpu","type":"mov","reloc":false,"type_num":9,"type2_num":0,"xrefs":[{"addr":10594,"type":"CODE"}]},{"offset":11108,"ptr":35024,"esil":"0x5d65,rip,+,rsi,=","refptr":true,"fcn_addr":10144,"fcn_last":11110,"size":7,"opcode":"lea rsi, [rip + 0x5d65]","disasm":"lea rsi, str.the_delimiter_must_be_a_single_character","bytes":"488d35655d0000","family":"cpu","type":"lea","reloc":false,"type_num":33,"type2_num":0,"refs":[{"addr":23909,"type":"DATA"},{"addr":35024,"type":"DATA"}]},{"offset":11115,"esil":"0x2afa,rip,=","refptr":false,"fcn_addr":10144,"fcn_last":11115,"size":2,"opcode":"jmp 0x2afa","disasm":"jmp 0x2afa","bytes":"eb8d","family":"cpu","type":"jmp","reloc":false,"type_num":1,"type2_num":0,"jump":11002,"refs":[{"addr":11002,"type":"CODE"}]}]}]}]
